{
  "BTC": "BTC/USD",
  "BCH": "BCH/USD",
  "BSV": "BSV/USD",
  "ETH": "ETH/USD",
  "ETH2": "ETH2/USD",
  "ETC": "ETC/USD",
  "LTC": "LTC/USD",
  "ZRX": "ZRX/USD",
  "USDC": "USDC/USD",
  "BAT": "BAT/USD",
  "LOOM": "LOOM/USD",
  "MANA": "MANA/USD",
  "KNC": "KNC/USD",
  "LINK": "LINK/USD",
  "DNT": "DNT/USD",
  "MKR": "MKR/USD",
  "CVC": "CVC/USD",
  "OMG": "OMG/USD",
  "GNT": "GNT/USD",
  "DAI": "DAI/USD",
  "SNT": "SNT/USD",
  "ZEC": "ZEC/USD",
  "XRP": "XRP/USD",
  "REP": "REP/USD",
  "XLM": "XLM/USD",
  "EOS": "EOS/USD",
  "XTZ": "XTZ/USD",
  "ALGO": "ALGO/USD",
  "DASH": "DASH/USD",
  "ATOM": "ATOM/USD",
  "OXT": "OXT/USD",
  "COMP": "COMP/USD",
  "ENJ": "ENJ/USD",
  "REPV2": "REPV2/USD",
  "BAND": "BAND/USD",
  "NMR": "NMR/USD",
  "CELO": "CELO/USD",
  "UMA": "UMA/USD",
  "LRC": "LRC/USD",
  "YFI": "YFI/USD",
  "UNI": "UNI/USD",
  "BAL": "BAL/USD",
  "REN": "REN/USD",
  "WBTC": "WBTC/USD",
  "NU": "NU/USD",
  "YFII": "YFII/USD",
  "FIL": "FIL/USD",
  "AAVE": "AAVE/USD",
  "BNT": "BNT/USD",
  "GRT": "GRT/USD",
  "SNX": "SNX/USD",
  "STORJ": "STORJ/USD",
  "SUSHI": "SUSHI/USD",
  "MATIC": "MATIC/USD",
  "SKL": "SKL/USD",
  "ADA": "ADA/USD",
  "ANKR": "ANKR/USD",
  "CRV": "CRV/USD",
  "ICP": "ICP/USD",
  "NKN": "NKN/USD",
  "OGN": "OGN/USD",
  "1INCH": "1INCH/USD",
  "USDT": "USDT/USD",
  "FORTH": "FORTH/USD",
  "CTSI": "CTSI/USD",
  "TRB": "TRB/USD",
  "POLY": "POLY/USD",
  "MIR": "MIR/USD",
  "RLC": "RLC/USD",
  "DOT": "DOT/USD",
  "SOL": "SOL/USD",
  "DOGE": "DOGE/USD",
  "MLN": "MLN/USD",
  "GTC": "GTC/USD",
  "AMP": "AMP/USD",
  "SHIB": "SHIB/USD",
  "CHZ": "CHZ/USD",
  "KEEP": "KEEP/USD",
  "LPT": "LPT/USD",
  "QNT": "QNT/USD",
  "BOND": "BOND/USD",
  "RLY": "RLY/USD",
  "CLV": "CLV/USD",
  "FARM": "FARM/USD",
  "MASK": "MASK/USD",
  "FET": "FET/USD",
  "PAX": "PAX/USD",
  "ACH": "ACH/USD",
  "ASM": "ASM/USD",
  "PLA": "PLA/USD",
  "RAI": "RAI/USD",
  "TRIBE": "TRIBE/USD",
  "ORN": "ORN/USD",
  "IOTX": "IOTX/USD",
  "UST": "UST/USD",
  "QUICK": "QUICK/USD",
  "AXS": "AXS/USD",
  "REQ": "REQ/USD",
  "WLUNA": "WLUNA/USD",
  "TRU": "TRU/USD",
  "RAD": "RAD/USD",
  "COTI": "COTI/USD",
  "DDX": "DDX/USD",
  "SUKU": "SUKU/USD",
  "RGT": "RGT/USD",
  "XYO": "XYO/USD",
  "ZEN": "ZEN/USD",
  "AUCTION": "AUCTION/USD",
  "BUSD": "BUSD/USD",
  "JASMY": "JASMY/USD",
  "WCFG": "WCFG/USD",
  "BTRST": "BTRST/USD",
  "AGLD": "AGLD/USD",
  "AVAX": "AVAX/USD",
  "FX": "FX/USD",
  "TRAC": "TRAC/USD",
  "LCX": "LCX/USD",
  "ARPA": "ARPA/USD",
  "BADGER": "BADGER/USD",
  "KRL": "KRL/USD",
  "PERP": "PERP/USD",
  "RARI": "RARI/USD",
  "DESO": "DESO/USD",
  "API3": "API3/USD",
  "NCT": "NCT/USD",
  "SHPING": "SHPING/USD",
  "UPI": "UPI/USD",
  "CRO": "CRO/USD",
  "AVT": "AVT/USD",
  "MDT": "MDT/USD",
  "VGX": "VGX/USD",
  "ALCX": "ALCX/USD",
  "COVAL": "COVAL/USD",
  "FOX": "FOX/USD",
  "MUSD": "MUSD/USD",
  "GALA": "GALA/USD",
  "POWR": "POWR/USD",
  "GYEN": "GYEN/USD",
  "ALICE": "ALICE/USD",
  "INV": "INV/USD",
  "LQTY": "LQTY/USD",
  "PRO": "PRO/USD",
  "SPELL": "SPELL/USD",
  "ENS": "ENS/USD",
  "DIA": "DIA/USD",
  "BLZ": "BLZ/USD",
  "CTX": "CTX/USD",
  "ERN": "ERN/USD",
  "IDEX": "IDEX/USD",
  "MCO2": "MCO2/USD",
  "POLS": "POLS/USD",
  "SUPER": "SUPER/USD",
  "UNFI": "UNFI/USD",
  "STX": "STX/USD",
  "KSM": "KSM/USD",
  "GODS": "GODS/USD",
  "IMX": "IMX/USD",
  "RBN": "RBN/USD",
  "BICO": "BICO/USD",
  "GFI": "GFI/USD",
  "GLM": "GLM/USD",
  "MPL": "MPL/USD",
  "PLU": "PLU/USD",
  "SAND": "SAND/USD",
  "FIDA": "FIDA/USD",
  "ORCA": "ORCA/USD",
  "CRPT": "CRPT/USD",
  "QSP": "QSP/USD",
  "RNDR": "RNDR/USD",
  "SYN": "SYN/USD",
  "AIOZ": "AIOZ/USD",
  "AERGO": "AERGO/USD",
  "HIGH": "HIGH/USD",
  "FLOW": "FLOW/USD",
  "ROSE": "ROSE/USD",
  "OP": "OP/USD",
  "APE": "APE/USD",
  "MINA": "MINA/USD",
  "BIT": "BIT/USD",
  "GMT": "GMT/USD",
  "GST": "GST/USD",
  "C98": "C98/USD",
  "GAL": "GAL/USD"
}
