{
  "interval": 60000,
  "priceAggregator": "median",
  "defaultSource": [
    "probit"
  ],
  "sourceTimeout": 50000,
  "maxPriceDeviationPercent": 25,
  "evmChainId": 1,
  "tokens": {
    "DOGE": {},
    "BTC": {},
    "CHZ": {},
    "ATOM": {},
    "XRP": {},
    "BCH": {},
    "TRX": {},
    "AXS": {},
    "COMP": {},
    "LTC": {},
    "LEO": {},
    "RVN": {},
    "UNI": {},
    "SHIB": {},
    "SUSHI": {},
    "RUNE": {},
    "ETH": {},
    "MANA": {},
    "OMG": {},
    "EOS": {},
    "VRA": {},
    "XEM": {},
    "BNB": {},
    "CNS": {},
    "ALGO": {},
    "SRM": {},
    "LINK": {},
    "QTUM": {},
    "RNDR": {},
    "XLM": {},
    "ENJ": {},
    "MATIC": {},
    "LRC": {},
    "NEO": {},
    "ZIL": {},
    "WAVES": {},
    "FRONT": {},
    "ETC": {},
    "ONT": {},
    "DOT": {},
    "CRO": {},
    "SNX": {},
    "ONG": {},
    "FTM": {},
    "XTZ": {},
    "ZRX": {},
    "FTT": {},
    "BAND": {},
    "ONE": {},
    "KCS": {},
    "BAT": {},
    "HOT": {},
    "HT": {},
    "BSV": {},
    "SAND": {},
    "XDC": {},
    "MKR": {},
    "XYM": {},
    "NEXO": {},
    "BTG": {},
    "YFI": {},
    "TUSD": {},
    "ICX": {},
    "USDC": {},
    "TOMO": {},
    "REN": {},
    "OGN": {},
    "BTS": {},
    "LSK": {},
    "BNT": {},
    "HIVE": {},
    "ARDR": {},
    "KNC": {},
    "REP": {},
    "DGB": {},
    "SXP": {},
    "DAI": {},
    "BAL": {},
    "JST": {},
    "NMR": {},
    "RSR": {},
    "YFII": {},
    "UTK": {},
    "PUNDIX": {},
    "KLAY": {},
    "STEEM": {},
    "ERG": {},
    "SNT": {},
    "SATT": {},
    "VLX": {},
    "TLOS": {},
    "DEXA": {},
    "ELA": {},
    "PANDO": {},
    "REV": {},
    "GAS": {},
    "OKB": {},
    "ORBS": {},
    "ZKS": {},
    "ARK": {},
    "BCD": {},
    "SOLO": {},
    "PRE": {},
    "UBX": {},
    "SKEY": {},
    "ENQ": {},
    "TRR": {},
    "RWN": {},
    "ELCASH": {}
  }
}
